macho/__init__.py
macho/main.py
macho/bloom_filter/__init__.py
macho/bloom_filter/bloom.py
macho/dashboard/__init__.py
macho/dashboard/dashboard.py
macho/dashboard/launcher.py
macho/dashboard/pages/1_general_page.py
macho/dashboard/pages/2_requests_page.py
macho/dashboard/pages/3_lifespan_page.py
macho/dashboard/pages/4_latency_page.py
macho/errors/__init__.py
macho/errors/exceptions.py
macho/logging/__init__.py
macho/logging/logger_config.py
macho/models/__init__.py
macho/models/models.py
macho/utility/__init__.py
macho/utility/utils.py
macho-0.0.1.dist-info/licenses/LICENSE
macho-0.0.1.dist-info/METADATA
macho-0.0.1.dist-info/WHEEL
macho-0.0.1.dist-info/top_level.txt
macho-0.0.1.dist-info/RECORD
