Metadata-Version: 2.4
Name: macho
Version: 0.0.1
Summary: Macho is a fast, memory-efficient in-memory cache with support for sharding, TTL, and pluggable eviction strategies like LRU, FIFO and Random.
Author-email: HysingerDev <HysingerDev@gmail.com>
License: MIT License
Project-URL: Homepage, https://github.com/MassivelyOverthinking/Macho
Project-URL: Documentation, https://github.com/MassivelyOverthinking/Macho
Project-URL: Source, https://github.com/MassivelyOverthinking/Macho
Project-URL: Issues, https://github.com/MassivelyOverthinking/Macho
Keywords: caching,cache,distributed cache,memory efficiency,in-memory,eviction strategies,lru,fifo,time-to-live,sharding,bloom filter,streamlit,metrics,interning,lightweight,lightweight classes,high-performance,probabilistic data structures
Classifier: Development Status :: 3 - Alpha
Classifier: Intended Audience :: Developers
Classifier: License :: OSI Approved :: MIT License
Classifier: Operating System :: OS Independent
Classifier: Programming Language :: Python
Classifier: Programming Language :: Python :: 3
Classifier: Programming Language :: Python :: 3.8
Classifier: Programming Language :: Python :: 3.9
Classifier: Programming Language :: Python :: 3.10
Classifier: Programming Language :: Python :: 3.11
Classifier: Programming Language :: Python :: 3.12
Classifier: Topic :: Software Development :: Libraries
Classifier: Topic :: Utilities
Requires-Python: >=3.8
License-File: LICENSE
Requires-Dist: bitarray>=3.5.0
Requires-Dist: mmh3>=5.1.0
Requires-Dist: pandas>=2.3.1
Requires-Dist: plotly>=6.3.0
Requires-Dist: streamlit>=1.48.1
Provides-Extra: dev
Requires-Dist: pytest>=8.4.1; extra == "dev"
Requires-Dist: pympler>=1.1; extra == "dev"
Requires-Dist: iniconfig>=2.1.0; extra == "dev"
Requires-Dist: pluggy>=1.6.0; extra == "dev"
Requires-Dist: packaging>=25.0; extra == "dev"
Requires-Dist: Pygments>=2.19.2; extra == "dev"
Dynamic: license-file
